rinoh/__init__.py
rinoh/__main__.py
rinoh/annotation.py
rinoh/attribute.py
rinoh/backend/__init__.py
rinoh/backend/pdf/__init__.py
rinoh/backend/pdf/cos.py
rinoh/backend/pdf/filter.py
rinoh/backend/pdf/pdfdoccodec.py
rinoh/backend/pdf/reader.py
rinoh/backend/pdf/util.py
rinoh/backend/pdf/xobject/__init__.py
rinoh/backend/pdf/xobject/icc/__init__.py
rinoh/backend/pdf/xobject/icc/sRGB_IEC61966-2-1_black_scaled.icc
rinoh/backend/pdf/xobject/icc/sRGB_IEC61966-2-1_black_scaled.txt
rinoh/backend/pdf/xobject/jpeg.py
rinoh/backend/pdf/xobject/png.py
rinoh/backend/pdf/xobject/purepng.py
rinoh/color.py
rinoh/csl_formatter.py
rinoh/data/fonts/adobe14/Courier-Bold.afm
rinoh/data/fonts/adobe14/Courier-BoldOblique.afm
rinoh/data/fonts/adobe14/Courier-Oblique.afm
rinoh/data/fonts/adobe14/Courier.afm
rinoh/data/fonts/adobe14/Helvetica-Bold.afm
rinoh/data/fonts/adobe14/Helvetica-BoldOblique.afm
rinoh/data/fonts/adobe14/Helvetica-Oblique.afm
rinoh/data/fonts/adobe14/Helvetica.afm
rinoh/data/fonts/adobe14/MustRead.html
rinoh/data/fonts/adobe14/Symbol.afm
rinoh/data/fonts/adobe14/Times-Bold.afm
rinoh/data/fonts/adobe14/Times-BoldItalic.afm
rinoh/data/fonts/adobe14/Times-Italic.afm
rinoh/data/fonts/adobe14/Times-Roman.afm
rinoh/data/fonts/adobe14/ZapfDingbats.afm
rinoh/data/fonts/zapfdingbats.txt
rinoh/data/hyphen/hyph_en_US.dic
rinoh/data/stylesheets/base14.rts
rinoh/data/stylesheets/sphinx.rts
rinoh/data/stylesheets/sphinx_article.rts
rinoh/data/xml/catalog
rinoh/data/xml/docutils/docutils.dtd
rinoh/data/xml/docutils/soextblx.dtd
rinoh/data/xml/w3c-entities/html5-uppercase.ent
rinoh/data/xml/w3c-entities/htmlmathml-f.ent
rinoh/data/xml/w3c-entities/htmlmathml.ent
rinoh/data/xml/w3c-entities/isoamsa.ent
rinoh/data/xml/w3c-entities/isoamsb.ent
rinoh/data/xml/w3c-entities/isoamsc.ent
rinoh/data/xml/w3c-entities/isoamsn.ent
rinoh/data/xml/w3c-entities/isoamso.ent
rinoh/data/xml/w3c-entities/isoamsr.ent
rinoh/data/xml/w3c-entities/isobox.ent
rinoh/data/xml/w3c-entities/isocyr1.ent
rinohtype-0.5.4.dist-info/entry_points.txt
rinohtype-0.5.4.dist-info/LICENSE
rinohtype-0.5.4.dist-info/WHEEL
rinohtype-0.5.4.dist-info/METADATA
rinohtype-0.5.4.dist-info/RECORD
