Metadata-Version: 2.1
Name: rinohtype
Version: 0.5.4
Summary: The Python document processor
Home-page: https://github.com/brechtm/rinohtype
License: AGPL-3.0-only
Keywords: typesetting,rst,pdf,opentype
Author: Brecht Machiels
Author-email: brecht@mos6581.org
Requires-Python: >=3.7.0,<4.0.0
Classifier: Development Status :: 4 - Beta
Classifier: Environment :: Console
Classifier: Environment :: Other Environment
Classifier: Environment :: Web Environment
Classifier: Intended Audience :: Developers
Classifier: Intended Audience :: End Users/Desktop
Classifier: License :: OSI Approved :: GNU Affero General Public License v3
Classifier: Operating System :: OS Independent
Classifier: Programming Language :: Python :: 3
Classifier: Programming Language :: Python :: 3.10
Classifier: Programming Language :: Python :: 3.7
Classifier: Programming Language :: Python :: 3.8
Classifier: Programming Language :: Python :: 3.9
Classifier: Programming Language :: Python :: Implementation :: CPython
Classifier: Programming Language :: Python :: Implementation :: PyPy
Classifier: Topic :: Printing
Classifier: Topic :: Software Development :: Libraries :: Python Modules
Classifier: Topic :: Text Processing :: Fonts
Classifier: Topic :: Text Processing :: Markup
Classifier: Topic :: Text Processing :: Markup :: XML
Requires-Dist: Sphinx (>=2.2.1)
Requires-Dist: appdirs (>=1.4.3,<2.0.0)
Requires-Dist: docutils (>=0.15)
Requires-Dist: importlib-metadata (>=0.21); python_version < "3.8"
Requires-Dist: packaging (>=14.0)
Requires-Dist: recommonmark (>=0.6.0)
Requires-Dist: rinoh-typeface-dejavuserif (>=0.1.3,<0.2.0)
Requires-Dist: rinoh-typeface-texgyrecursor (>=0.1.1,<0.2.0)
Requires-Dist: rinoh-typeface-texgyreheros (>=0.1.1,<0.2.0)
Requires-Dist: rinoh-typeface-texgyrepagella (>=0.1.1,<0.2.0)
Project-URL: Bug Tracker, https://github.com/brechtm/rinohtype/issues
Project-URL: Changelog, http://www.mos6581.org/rinohtype/master/changelog.html
Project-URL: Documentation, http://www.mos6581.org/rinohtype/master
Project-URL: Repository, https://github.com/brechtm/rinohtype
